{
    "abaddon": 1,
    "alchemist": 2,
    "ancient_apparition": 3,
    "anti-mage": 4,
    "arc_warden": 5,
    "axe": 6,
    "bane": 7,
    "batrider": 8,
    "beastmaster": 9,
    "bloodseeker": 10,
    "bounty_hunter": 11,
    "brewmaster": 12,
    "bristleback": 13,
    "broodmother": 14,
    "centaur_warrunner": 15,
    "chaos_knight": 16,
    "chen": 17,
    "clinkz": 18,
    "clockwerk": 19,
    "crystal_maiden": 20,
    "dark_seer": 21,
    "dark_willow": 22,
    "dawnbreaker": 23,
    "dazzle": 24,
    "death_prophet": 25,
    "disruptor": 26,
    "doom": 27,
    "dragon_knight": 28,
    "drow_ranger": 29,
    "earth_spirit": 30,
    "earthshaker": 31,
    "elder_titan": 32,
    "ember_spirit": 33,
    "enchantress": 34,
    "enigma": 35,
    "faceless_void": 36,
    "grimstroke": 37,
    "gyrocopter": 38,
    "hoodwink": 39,
    "huskar": 40,
    "invoker": 41,
    "io": 42,
    "jakiro": 43,
    "juggernaut": 44,
    "keeper_of_the_light": 45,
    "kunkka": 46,
    "legion_commander": 47,
    "leshrac": 48,
    "lich": 49,
    "lifestealer": 50,
    "lina": 51,
    "lion": 52,
    "lone_druid": 53,
    "luna": 54,
    "lycan": 55,
    "magnus": 56,
    "marci": 57,
    "mars": 58,
    "medusa": 59,
    "meepo": 60,
    "mirana": 61,
    "monkey_king": 62,
    "morphling": 63,
    "muerta": 64,
    "naga_siren": 65,
    "natures_prophet": 66,
    "necrophos": 67,
    "night_stalker": 68,
    "nyx_assassin": 69,
    "ogre_magi": 70,
    "omniknight": 71,
    "oracle": 72,
    "outworld_destroyer": 73,
    "pangolier": 74,
    "phantom_assassin": 75,
    "phantom_lancer": 76,
    "phoenix": 77,
    "primal_beast": 78,
    "puck": 79,
    "pudge": 80,
    "pugna": 81,
    "queen_of_pain": 82,
    "razor": 83,
    "riki": 84,
    "rubick": 85,
    "sand_king": 86,
    "shadow_demon": 87,
    "shadow_fiend": 88,
    "shadow_shaman": 89,
    "silencer": 90,
    "skywrath_mage": 91,
    "slardar": 92,
    "slark": 93,
    "snapfire": 94,
    "sniper": 95,
    "spectre": 96,
    "spirit_breaker": 97,
    "storm_spirit": 98,
    "sven": 99,
    "techies": 100,
    "templar_assassin": 101,
    "terrorblade": 102,
    "tidehunter": 103,
    "timbersaw": 104,
    "tinker": 105,
    "tiny": 106,
    "treant_protector": 107,
    "troll_warlord": 108,
    "tusk": 109,
    "underlord": 110,
    "undying": 111,
    "ursa": 112,
    "vengeful_spirit": 113,
    "venomancer": 114,
    "viper": 115,
    "visage": 116,
    "void_spirit": 117,
    "warlock": 118,
    "weaver": 119,
    "windranger": 120,
    "winter_wyvern": 121,
    "witch_doctor": 122,
    "wraith_king": 123,
    "zeus": 124
}